MANIFEST.in
README.txt
setup.cfg
setup.py
hironsan/__init__.py
hironsan/__init__.pyc
hironsan/corpus/__init__.py
hironsan/corpus/__init__.pyc
hironsan/corpus/hiron_corpus.pickle
hironsan/corpus/iob_sents.txt
hironsancorpus.egg-info/PKG-INFO
hironsancorpus.egg-info/SOURCES.txt
hironsancorpus.egg-info/dependency_links.txt
hironsancorpus.egg-info/top_level.txt
tests/__init__.py