Metadata-Version: 1.1
Name: hironsancorpus
Version: 0.1.0
Summary: Japanese IOB2 tagged corpus for named entity recognition.
Home-page: https://github.com/Hironsan/hironsan_corpus
Author: Hironsan
Author-email: light.tree.1.13@gmail.com
License: MIT
Keywords: corpus,IOB,named entity recognition,japanese corpus
Platform: UNKNOWN
Classifier: Development Status :: 3 - Alpha
Classifier: Intended Audience :: Developers
Classifier: License :: OSI Approved :: MIT License
Classifier: Programming Language :: Python :: 2
Classifier: Programming Language :: Python :: 3
